[{"team": "Idaho", "player": "Kristian Gonzalez", "position": "G", "mpg": 18.0, "ppg": 18.0, "source": "espn"}, {"team": "Idaho", "player": "Jackson Rasmussen", "position": "F", "mpg": 30.9, "ppg": 13.9, "source": "espn"}, {"team": "Idaho", "player": "Kolton Mitchell", "position": "G", "mpg": 30.3, "ppg": 13.7, "source": "espn"}, {"team": "Idaho", "player": "Biko Johnson", "position": "G", "mpg": 27.6, "ppg": 12.4, "source": "espn"}, {"team": "Idaho", "player": "Isaiah Brickner", "position": "G", "mpg": 20.4, "ppg": 12.1, "source": "espn"}, {"team": "Idaho", "player": "Brody Rowbury", "position": "F", "mpg": 24.4, "ppg": 7.8, "source": "espn"}, {"team": "Idaho", "player": "Jack Payne", "position": "G", "mpg": 21.8, "ppg": 6.7, "source": "espn"}, {"team": "Idaho", "player": "Seth Joba", "position": "F", "mpg": 17.3, "ppg": 5.3, "source": "espn"}, {"team": "Idaho", "player": "Miles Klapper", "position": "G", "mpg": 12.1, "ppg": 3.8, "source": "espn"}, {"team": "Idaho", "player": "Trevon Blassingame", "position": "G", "mpg": 16.8, "ppg": 3.7, "source": "espn"}, {"team": "Idaho", "player": "Aidan Sevilla", "position": "G", "mpg": 6.0, "ppg": 1.8, "source": "espn"}, {"team": "Idaho", "player": "Ewan Steele", "position": "F", "mpg": 6.7, "ppg": 1.6, "source": "espn"}]